<?xml version="1.0" encoding="UTF-8"?>
<!DOCTYPE Custom PUBLIC "sailpoint.dtd" "sailpoint.dtd">
<Custom name="ELE_Correlation_Custom_Object">
    <Attributes>
        <Map>
            <entry key="blackline">
                <value>
                    <Map>
                        <entry key="accountAttribute" value="emailAddress"/>
                        <entry key="searchAttribute" value="emailAddress"/>
                        <entry key="searchClass" value="Link"/>
                    </Map>
                </value>
            </entry>
            <entry key="collateral">
                <value>
                    <Map>
                        <entry key="accountAttribute" value="UserAD"/>
                        <entry key="searchAttribute" value="loginid"/>
                        <entry key="searchClass" value="Link"/>
                    </Map>
                </value>
            </entry>
            <entry key="contpaq bancos">
                <value>
                    <Map>
                        <entry key="accountAttribute" value="Codigo"/>
                        <entry key="searchAttribute" value="loginid"/>
                        <entry key="searchClass" value="Link"/>
                    </Map>
                </value>
            </entry>
            <entry key="contpaq commercial">
                <value>
                    <Map>
                        <entry key="accountAttribute" value="CLAVE"/>
                        <entry key="searchAttribute" value="loginid"/>
                        <entry key="searchClass" value="Link"/>
                    </Map>
                </value>
            </entry>
             <entry key="drivercare">
                <value>
                    <Map>
                        <entry key="accountAttribute" value="Email"/>
                        <entry key="searchAttribute" value="emailAddress"/>
                        <entry key="searchClass" value="Link"/>
                    </Map>
                </value>
            </entry>
             <entry key="einvoicing">
                <value>
                    <Map>
                        <entry key="accountAttribute" value="Email"/>
                        <entry key="searchAttribute" value="emailAddress"/>
                        <entry key="searchClass" value="Link"/>
                    </Map>
                </value>
            </entry>
            <entry key="oasis">
                <value>
                    <Map>
                        <entry key="accountAttribute" value="Email Address"/>
                        <entry key="searchAttribute" value="emailAddress"/>
                        <entry key="searchClass" value="Link"/>
                    </Map>
                </value>
            </entry>
            <entry key="ms dynamics">
                <value>
                    <Map>
                        <entry key="accountAttribute" value="emailaddress"/>
                        <entry key="searchAttribute" value="emailAddress"/>
                        <entry key="searchClass" value="Link"/>
                    </Map>
                </value>
            </entry>
            <entry key="great plains">
                <value>
                    <Map>
                        <entry key="accountAttribute" value="UserID"/>
                        <entry key="searchAttribute" value="loginid"/>
                        <entry key="searchClass" value="Link"/>
                    </Map>
                </value>
            </entry>
            <entry key="intelliclaim">
                <value>
                    <Map>
                        <entry key="accountAttribute" value="SecurityToken"/>
                        <entry key="searchAttribute" value="loginid"/>
                        <entry key="searchClass" value="Link"/>
                    </Map>
                </value>
            </entry>
             <entry key="onbase">
                <value>
                    <Map>
                        <entry key="accountAttribute" value="UserName"/>
                        <entry key="searchAttribute" value="loginid"/>
                        <entry key="searchClass" value="Link"/>
                    </Map>
                </value>
            </entry>
            <entry key="nvp">
                <value>
                    <Map>
                        <entry key="accountAttribute" value="adusername"/>
                        <entry key="searchAttribute" value="loginid"/>
                        <entry key="searchClass" value="Link"/>
                    </Map>
                </value>
            </entry>
            <entry key="fdc billing">
                <value>
                    <Map>
                        <entry key="accountAttribute" value="emailaddress"/>
                        <entry key="searchAttribute" value="emailAddress"/>
                        <entry key="searchClass" value="Link"/>
                    </Map>
                </value>
            </entry>
            <entry key="onestream">
                <value>
                    <Map>
                        <entry key="accountAttribute" value="emailAddress"/>
                        <entry key="searchAttribute" value="emailAddress"/>
                        <entry key="searchClass" value="Link"/>
                    </Map>
                </value>
            </entry>
            <entry key="database">
                <value>
                    <Map>
                        <entry key="accountAttribute" value="native_identity"/>
                        <entry key="searchAttribute" value="loginid"/>
                        <entry key="searchClass" value="Link"/>
                    </Map>
                </value>
            </entry>
            <entry key="servicenow">
                <value>
                    <Map>
                        <entry key="accountAttribute" value="email"/>
                        <entry key="searchAttribute" value="emailAddress"/>
                        <entry key="searchClass" value="Link"/>
                    </Map>
                </value>
            </entry>
        </Map>
    </Attributes>
</Custom>